{
  "layer": "default",
  "locked": false,
  "objectProperties": {
    "resizable": true,
    "movable": true,
    "selectable": true,
    "rotatable": true
  },
  "$schema": "/json-schema/d.json",
  "type": "Widget",
  "position": {
    "x": 872.024658203125,
    "y": 314.0571594238281
  },
  "size": {
    "height": 472.04315727282494,
    "width": 638.6949737735961
  },
  "zIndex": 3,
  "angle": 0,
  "typeSettings": {
    "widgetPath": "src/Visualizations/widgets/c361077d-2675-4789-b978-f4c71f882568.json"
  },
  "styles": {
    "background-color": "#333333",
    "border-color": "#1a1a1a",
    "border-style": "solid",
    "border-width": "1px",
    "border-radius": "0",
    "filter": "drop-shadow(0px 0px 0px #939393)"
  }
}
